sniper/__init__.py
sniper/ami.py
sniper/aws.py
sniper/cli.py
sniper/engine.py
sniper/instance.py
sniper/region.py
sniper/resourcegroups.py
sniper/snapshot.py
sniper/spreadsheet.py
pz_sniper-0.1.3.dist-info/LICENSE
pz_sniper-0.1.3.dist-info/METADATA
pz_sniper-0.1.3.dist-info/WHEEL
pz_sniper-0.1.3.dist-info/entry_points.txt
pz_sniper-0.1.3.dist-info/top_level.txt
pz_sniper-0.1.3.dist-info/RECORD
