Metadata-Version: 2.1
Name: pz-sniper
Version: 0.1.3
Summary: kill resources across all regions in AWS in a targetted fashion
License-File: LICENSE
Requires-Dist: boto3
Requires-Dist: botocore
Requires-Dist: argparse
